{
  "bvid": "BV1pbK66TEmp",
  "aid": 116947513507849,
  "title": "DeepseekV4正式版一句话生成马里奥",
  "up_name": "しょうぎのハンカチ",
  "up_mid": 136554747,
  "up_face": "https://i0.hdslb.com/bfs/face/d3f11f5a7524213e02abc5989eb88a379a0582e0.jpg",
  "desc": "",
  "duration": 144,
  "pub_time_ts": 1784477459,
  "pub_time": "2026-07-20 00:10:59",
  "stats": {
    "view": 4780,
    "like": 92,
    "coin": 4,
    "favorite": 23,
    "share": 22,
    "reply": 56
  },
  "tags": [],
  "share_links": [],
  "download_links": [],
  "comments_links": {
    "share": [],
    "download": []
  },
  "all_share_links": [],
  "all_download_links": [],
  "comments": {
    "total": 19,
    "top_comments": [
      {
        "user": "水月泠音",
        "message": "直接震惊瘫坐[笑哭]\n快端上来吧，20号了已经",
        "likes": 21,
        "time": "2026-07-20 01:25:12"
      },
      {
        "user": "古华多萝",
        "message": "正式版上了吗，刚刚一过0点专家模式对话就繁忙了[笑哭]",
        "likes": 19,
        "time": "2026-07-20 00:13:00"
      },
      {
        "user": "梅花7__",
        "message": "你说原版我都信[doge]",
        "likes": 12,
        "time": "2026-07-20 01:04:09"
      },
      {
        "user": "坚定的共产主义接班人",
        "message": "要重新定义中旬了",
        "likes": 8,
        "time": "2026-07-20 06:34:18"
      },
      {
        "user": "大半夜未眠",
        "message": "我就在找这个，全是马里奥赛车却没有马里奥，结果立刻就有人上传了",
        "likes": 8,
        "time": "2026-07-20 00:12:05"
      },
      {
        "user": "ArtChang",
        "message": "这完全可以跑一个 hd2d 风格的",
        "likes": 5,
        "time": "2026-07-20 01:09:10"
      },
      {
        "user": "唯物主义之神",
        "message": "吃完了？[doge]",
        "likes": 4,
        "time": "2026-07-20 00:16:35"
      },
      {
        "user": "しょうぎのハンカチ",
        "message": "@斗门不断修正公示",
        "likes": 3,
        "time": "2026-07-20 00:13:36"
      }
    ],
    "up_replies_with_links": []
  }
}