{
  "bvid": "BV1TLNC6SEs6",
  "aid": 116910737852632,
  "title": "dsv4 正式版 测试",
  "up_name": "2258ppq",
  "up_mid": 1019564727,
  "up_face": "https://i0.hdslb.com/bfs/face/0c7a47887fa80c0bef93de1b68f7a2f8082ce8c9.jpg",
  "desc": "看看效果就行了，不用听我说什么，因为我自己也听不清。见谅。\n字幕太多了，只修了前面一点。",
  "duration": 1424,
  "pub_time_ts": 1783916527,
  "pub_time": "2026-07-13 12:22:07",
  "stats": {
    "view": 8523,
    "like": 124,
    "coin": 32,
    "favorite": 27,
    "share": 17,
    "reply": 165
  },
  "tags": [],
  "share_links": [],
  "download_links": [],
  "comments_links": {
    "share": [],
    "download": []
  },
  "all_share_links": [],
  "all_download_links": [],
  "comments": {
    "total": 19,
    "top_comments": [
      {
        "user": "高级作战记录",
        "message": "梁圣快更新吧，让我账户多2亿token我也愿意啊😭",
        "likes": 72,
        "time": "2026-07-13 15:50:46"
      },
      {
        "user": "冬眠の松鼠_",
        "message": "能帮我完成遗志吗？[笑哭]我当时预告下一期做《三国杀》和《植物大战僵尸》，还没开始做就坠机了",
        "likes": 45,
        "time": "2026-07-13 12:39:11"
      },
      {
        "user": "玉红597",
        "message": "新版dsv4的测试效果确实有意思，感觉在特定场景下的逻辑能力又提升了。测试新模型最怕的就是官方接口不稳定或者排队，我一般会把测试流量切到 infistar.ai 这个通道上，线路比较稳，而且后台的调用记录和Token消耗明细查起来很直观，非常适合拿来做新模型的性能对照和基准测试。",
        "likes": 34,
        "time": "2026-07-13 17:34:01"
      },
      {
        "user": "张某人就是i",
        "message": "核弹震惊瘫坐，仿佛看到我和椅子爆炸[喜欢]",
        "likes": 7,
        "time": "2026-07-13 13:32:07"
      },
      {
        "user": "1505100212",
        "message": "“生成一个《星际开拓者》单文件HTML游戏。包含：10x10网格地图（随机山脉/平原），玩家与AI各控1基地。需实现：1) 点击单位A*寻路移动，2) 每回合采集黄金并消耗升级攻击力，3) AI自动追踪最近玩家单位并攻击，4) 视野迷雾（仅显示单位周围2格），5) 顶部实时显示血量/金币/回合数，6) 攻防动画与胜负弹窗。代码要求无bug、界面赛博朋克风格。”",
        "likes": 6,
        "time": "2026-07-13 14:14:11"
      },
      {
        "user": "2258ppq",
        "message": "还有什么想测的发在评论区[鸣潮_哇]",
        "likes": 6,
        "time": "2026-07-13 12:26:29"
      },
      {
        "user": "八荒_斩魂",
        "message": "真把孩子给馋哭了。😭",
        "likes": 5,
        "time": "2026-07-13 12:44:29"
      },
      {
        "user": "飯綱九龍",
        "message": "up能试一下这个吗，多谢啦，会不会难度有点大了[笑哭][笑哭]\n\n## 任务目标\n创建一个网页版“模仿原版50层魔塔”的完整小游戏，单HTML文件实现。\n\n## 核心要求\n1. 高度还原原版50层魔塔，不确定的细节自行搜索资料确认。\n2. 纯HTML+CSS+JavaScript，无外部依赖，单文件。\n3. 必须完整可通关，包含全部50层，完成后自动多轮测试debug。\n\n## 必须还原的机制\n\n**角色属性**：生命、攻击、防御、经验、等级、金币。\n\n**物品**：黄/蓝/红钥匙、红宝石(+攻击)、蓝宝石(+防御)、血瓶、楼层传送器、破墙镐等。\n\n**战斗**：数值计算制（非随机），原版伤害",
        "likes": 4,
        "time": "2026-07-13 16:04:13"
      }
    ],
    "up_replies_with_links": []
  }
}